deploy/__init__.py
deploy/git_manager.py
deploy/model_company_updater.py
deploy/readme_updater.py
deploy/s3_manager.py
deploy/version_manager.py
looqbox_commons/__init__.py
looqbox_commons/src/__init__.py
looqbox_commons/src/main/__init__.py
looqbox_commons/src/main/const.py
looqbox_commons/src/main/config/__init__.py
looqbox_commons/src/main/config/obj_mapper_config.py
looqbox_commons/src/main/config/pydantic_configuration.py
looqbox_commons/src/main/data_holder/__init__.py
looqbox_commons/src/main/data_holder/data_holder.py
looqbox_commons/src/main/data_holder/key_creator.py
looqbox_commons/src/main/dot_notation/__init__.py
looqbox_commons/src/main/dot_notation/dot_notation.py
looqbox_commons/src/main/i18n/__init__.py
looqbox_commons/src/main/i18n/i18n_key_creator.py
looqbox_commons/src/main/ioc/__init__.py
looqbox_commons/src/main/ioc/ioc.py
looqbox_commons/src/main/ioc/model/__init__.py
looqbox_commons/src/main/ioc/model/base_bean.py
looqbox_commons/src/main/ioc/model/bean.py
looqbox_commons/src/main/ioc/model/component.py
looqbox_commons/src/main/ioc/model/configuration.py
looqbox_commons/src/main/logger/__init__.py
looqbox_commons/src/main/logger/logger.py
looqbox_commons/src/main/logger/logger_interface.py
looqbox_commons/src/main/logger/formatters/__init__.py
looqbox_commons/src/main/logger/formatters/base_formatter.py
looqbox_commons/src/main/logger/formatters/json_formatter.py
looqbox_commons/src/main/logger/formatters/stout_formatter.py
looqbox_commons/src/main/logger/handlers/__init__.py
looqbox_commons/src/main/object_mapper/__init__.py
looqbox_commons/src/main/object_mapper/object_mapper.py
looqbox_commons/src/main/object_mapper/test_model.py
looqbox_commons/src/main/path_manager/__init__.py
looqbox_commons/src/main/path_manager/path.py
looqbox_commons/src/main/resources/__init__.py
looqbox_commons/src/main/resources/logger_config/__init__.py
looqbox_commons/src/main/resources/logger_config/base_logger.json
looqbox_commons/src/main/utils/__init__.py
looqbox_commons-6.2.1.dist-info/METADATA
looqbox_commons-6.2.1.dist-info/WHEEL
looqbox_commons-6.2.1.dist-info/top_level.txt
looqbox_commons-6.2.1.dist-info/RECORD
