Metadata-Version: 2.2
Name: looqbox_commons
Version: 6.2.1
Summary: A package with utils functions to all response packages
Home-page: https://github.com/looqbox/python-package-commons/
Author: looqbox
Author-email: admin@looqbox.com
Classifier: Programming Language :: Python :: 3
Classifier: License :: OSI Approved :: MIT License
Classifier: Operating System :: OS Independent
Requires-Dist: boto3>=1.24.79
Requires-Dist: botocore>=1.27.79
Requires-Dist: pymongo>=4.1.1
Requires-Dist: numpy>=1.26.3
Requires-Dist: pydantic>=2.4.2
Dynamic: author
Dynamic: author-email
Dynamic: classifier
Dynamic: home-page
Dynamic: requires-dist
Dynamic: summary
